behavioral_biometrics/__init__.py
behavioral_biometrics/app.py
behavioral_biometrics/utils.py
behavioral_biometrics-0.1.1.dist-info/METADATA
behavioral_biometrics-0.1.1.dist-info/WHEEL
behavioral_biometrics-0.1.1.dist-info/top_level.txt
behavioral_biometrics-0.1.1.dist-info/RECORD
